qpmpc/__init__.py
qpmpc/exceptions.py
qpmpc/mpc_problem.py
qpmpc/mpc_qp.py
qpmpc/plan.py
qpmpc/solve_mpc.py
qpmpc/live_plots/__init__.py
qpmpc/live_plots/live_plot.py
qpmpc/live_plots/wheeled_inverted_pendulum_plot.py
qpmpc/systems/__init__.py
qpmpc/systems/wheeled_inverted_pendulum.py
qpmpc-3.1.0.dist-info/LICENSE
qpmpc-3.1.0.dist-info/WHEEL
qpmpc-3.1.0.dist-info/METADATA
qpmpc-3.1.0.dist-info/RECORD
