Metadata-Version: 2.1
Name: qpmpc
Version: 3.1.0
Summary: Linear time-variant model predictive control in Python.
Keywords: model,predictive,control,linear,time-varying
Author-email: Stéphane Caron <stephane.caron@normalesup.org>
Maintainer-email: Stéphane Caron <stephane.caron@normalesup.org>
Requires-Python: >=3.8
Classifier: Development Status :: 5 - Production/Stable
Classifier: Intended Audience :: Developers
Classifier: Intended Audience :: Science/Research
Classifier: License :: OSI Approved :: Apache Software License
Classifier: Operating System :: OS Independent
Classifier: Programming Language :: Python :: 3.8
Classifier: Programming Language :: Python :: 3.9
Classifier: Programming Language :: Python :: 3.10
Classifier: Programming Language :: Python :: 3.11
Classifier: Topic :: Scientific/Engineering :: Mathematics
Requires-Dist: qpsolvers >=1.8.0
Requires-Dist: loop-rate-limiters ; extra == "extras"
Project-URL: Changelog, https://github.com/stephane-caron/qpmpc/blob/main/CHANGELOG.md
Project-URL: Documentation, https://scaron.info/doc/qpmpc/
Project-URL: Homepage, https://github.com/stephane-caron/qpmpc
Project-URL: Source, https://github.com/stephane-caron/qpmpc
Project-URL: Tracker, https://github.com/stephane-caron/qpmpc/issues
Provides-Extra: extras
